medkit/__init__.py
medkit/_compat.py
medkit/_import.py
medkit/audio/__init__.py
medkit/audio/metrics/__init__.py
medkit/audio/metrics/diarization.py
medkit/audio/metrics/transcription.py
medkit/audio/preprocessing/__init__.py
medkit/audio/preprocessing/downmixer.py
medkit/audio/preprocessing/power_normalizer.py
medkit/audio/preprocessing/resampler.py
medkit/audio/segmentation/__init__.py
medkit/audio/segmentation/pa_speaker_detector.py
medkit/audio/segmentation/webrtc_voice_detector.py
medkit/audio/transcription/__init__.py
medkit/audio/transcription/doc_transcriber.py
medkit/audio/transcription/hf_transcriber.py
medkit/audio/transcription/sb_transcriber.py
medkit/audio/transcription/transcribed_text_document.py
medkit/core/__init__.py
medkit/core/_prov_graph.py
medkit/core/annotation.py
medkit/core/annotation_container.py
medkit/core/attribute.py
medkit/core/attribute_container.py
medkit/core/collection.py
medkit/core/conversion.py
medkit/core/data_item.py
medkit/core/dict_conv.py
medkit/core/doc_pipeline.py
medkit/core/document.py
medkit/core/id.py
medkit/core/operation.py
medkit/core/operation_desc.py
medkit/core/pipeline.py
medkit/core/prov_store.py
medkit/core/prov_tracer.py
medkit/core/store.py
medkit/core/audio/__init__.py
medkit/core/audio/annotation.py
medkit/core/audio/annotation_container.py
medkit/core/audio/audio_buffer.py
medkit/core/audio/document.py
medkit/core/audio/operation.py
medkit/core/audio/span.py
medkit/core/text/__init__.py
medkit/core/text/annotation.py
medkit/core/text/annotation_container.py
medkit/core/text/document.py
medkit/core/text/entity_attribute_container.py
medkit/core/text/entity_norm_attribute.py
medkit/core/text/operation.py
medkit/core/text/span.py
medkit/core/text/span_utils.py
medkit/core/text/umls_norm_attribute.py
medkit/core/text/utils.py
medkit/io/__init__.py
medkit/io/_brat_utils.py
medkit/io/_common.py
medkit/io/brat.py
medkit/io/doccano.py
medkit/io/rttm.py
medkit/io/spacy.py
medkit/io/srt.py
medkit_lib-0.16.0.dist-info/METADATA
medkit_lib-0.16.0.dist-info/WHEEL
medkit_lib-0.16.0.dist-info/licenses/LICENSE
medkit_lib-0.16.0.dist-info/RECORD
