Metadata-Version: 2.3
Name: medkit-lib
Version: 0.16.0
Summary: A Python library for a learning health system
Project-URL: Changelog, https://medkit.readthedocs.io/en/stable/changelog.html
Project-URL: Documentation, https://medkit.readthedocs.io
Project-URL: Issues, https://github.com/medkit-lib/medkit/issues
Project-URL: Source, https://github.com/medkit-lib/medkit
Author: HeKA Research Team
Maintainer-email: medkit maintainers <medkit-maintainers@inria.fr>
License-Expression: MIT
License-File: LICENSE
Keywords: bert,digital health,ehr,nlp,umls
Classifier: Development Status :: 3 - Alpha
Classifier: Intended Audience :: Developers
Classifier: Intended Audience :: Science/Research
Classifier: License :: OSI Approved :: MIT License
Classifier: Operating System :: OS Independent
Classifier: Programming Language :: Python :: 3
Classifier: Programming Language :: Python :: 3.8
Classifier: Programming Language :: Python :: 3.9
Classifier: Programming Language :: Python :: 3.10
Classifier: Programming Language :: Python :: 3.11
Classifier: Programming Language :: Python :: 3.12
Classifier: Topic :: Scientific/Engineering :: Artificial Intelligence
Classifier: Topic :: Scientific/Engineering :: Medical Science Apps.
Classifier: Topic :: Software Development
Requires-Python: >=3.8
Requires-Dist: anyascii
Requires-Dist: duptextfinder>=0.3.0
Requires-Dist: flashtext>=2.7
Requires-Dist: intervaltree
Requires-Dist: numpy
Requires-Dist: pyaml
Requires-Dist: pysimstring
Requires-Dist: requests
Requires-Dist: smart-open
Requires-Dist: soundfile
Requires-Dist: tqdm
Requires-Dist: typing-extensions>=4.6.0
Provides-Extra: all
Requires-Dist: edsnlp>=0.9; extra == 'all'
Requires-Dist: feather-format>=0.4; extra == 'all'
Requires-Dist: huggingface-hub; extra == 'all'
Requires-Dist: iamsystem>=0.6.0; extra == 'all'
Requires-Dist: nlstruct>=0.2; extra == 'all'
Requires-Dist: packaging; extra == 'all'
Requires-Dist: pandas>=1.4; extra == 'all'
Requires-Dist: pyannote-audio>=3.1; extra == 'all'
Requires-Dist: pyannote-core>=5.0; extra == 'all'
Requires-Dist: pyannote-metrics>=3.2.0; extra == 'all'
Requires-Dist: pyrush>=1.0; extra == 'all'
Requires-Dist: pysrt>=1.1.2; extra == 'all'
Requires-Dist: quickumls>=1.4; extra == 'all'
Requires-Dist: resampy>=0.4; extra == 'all'
Requires-Dist: sacremoses; extra == 'all'
Requires-Dist: scikit-learn>=1.3.2; extra == 'all'
Requires-Dist: sentencepiece; extra == 'all'
Requires-Dist: seqeval>=1.2.2; extra == 'all'
Requires-Dist: spacy>=3.4; extra == 'all'
Requires-Dist: speechbrain>=0.5; extra == 'all'
Requires-Dist: speechbrain>=1.0; extra == 'all'
Requires-Dist: torch>=2.1.1; extra == 'all'
Requires-Dist: torchaudio>=2.1.1; extra == 'all'
Requires-Dist: transformers>=4.21; extra == 'all'
Requires-Dist: unqlite>=0.9.6; extra == 'all'
Requires-Dist: webrtcvad>=2.0; extra == 'all'
Provides-Extra: docs
Requires-Dist: myst-nb; extra == 'docs'
Requires-Dist: numpydoc; extra == 'docs'
Requires-Dist: pandas; extra == 'docs'
Requires-Dist: sphinx; extra == 'docs'
Requires-Dist: sphinx-autoapi; extra == 'docs'
Requires-Dist: sphinx-autobuild; extra == 'docs'
Requires-Dist: sphinx-book-theme; extra == 'docs'
Requires-Dist: sphinx-design; extra == 'docs'
Requires-Dist: sphinxcontrib-mermaid; extra == 'docs'
Provides-Extra: edsnlp
Requires-Dist: edsnlp>=0.9; extra == 'edsnlp'
Provides-Extra: hf-entity-matcher
Requires-Dist: torch>=2.1.1; extra == 'hf-entity-matcher'
Requires-Dist: transformers>=4.21; extra == 'hf-entity-matcher'
Provides-Extra: hf-transcriber
Requires-Dist: torchaudio>=2.1.1; extra == 'hf-transcriber'
Requires-Dist: transformers>=4.21; extra == 'hf-transcriber'
Provides-Extra: hf-translator
Requires-Dist: sacremoses; extra == 'hf-translator'
Requires-Dist: sentencepiece; extra == 'hf-translator'
Requires-Dist: torch>=2.1.1; extra == 'hf-translator'
Requires-Dist: transformers>=4.21; extra == 'hf-translator'
Provides-Extra: hf-utils
Requires-Dist: transformers>=4.21; extra == 'hf-utils'
Provides-Extra: iamsystem-matcher
Requires-Dist: iamsystem>=0.6.0; extra == 'iamsystem-matcher'
Provides-Extra: metrics-diarization
Requires-Dist: pyannote-core>=5.0; extra == 'metrics-diarization'
Requires-Dist: pyannote-metrics>=3.2.0; extra == 'metrics-diarization'
Provides-Extra: metrics-ner
Requires-Dist: seqeval>=1.2.2; extra == 'metrics-ner'
Requires-Dist: torch>=2.1.1; extra == 'metrics-ner'
Requires-Dist: transformers>=4.21; extra == 'metrics-ner'
Provides-Extra: metrics-text-classification
Requires-Dist: scikit-learn>=1.3.2; extra == 'metrics-text-classification'
Provides-Extra: metrics-transcription
Requires-Dist: speechbrain>=1.0; extra == 'metrics-transcription'
Provides-Extra: nlstruct
Requires-Dist: huggingface-hub; extra == 'nlstruct'
Requires-Dist: nlstruct>=0.2; extra == 'nlstruct'
Requires-Dist: torch>=2.1.1; extra == 'nlstruct'
Provides-Extra: pa-speaker-detector
Requires-Dist: pyannote-audio>=3.1; extra == 'pa-speaker-detector'
Requires-Dist: torch>=2.1.1; extra == 'pa-speaker-detector'
Provides-Extra: quick-umls
Requires-Dist: packaging; extra == 'quick-umls'
Requires-Dist: quickumls>=1.4; extra == 'quick-umls'
Requires-Dist: unqlite>=0.9.6; extra == 'quick-umls'
Provides-Extra: resampler
Requires-Dist: resampy>=0.4; extra == 'resampler'
Provides-Extra: rush-sentence-tokenizer
Requires-Dist: pyrush>=1.0; extra == 'rush-sentence-tokenizer'
Provides-Extra: sb-transcriber
Requires-Dist: speechbrain>=0.5; extra == 'sb-transcriber'
Requires-Dist: torch>=2.1.1; extra == 'sb-transcriber'
Requires-Dist: transformers>=4.21; extra == 'sb-transcriber'
Provides-Extra: spacy
Requires-Dist: spacy>=3.4; extra == 'spacy'
Provides-Extra: srt-io-converter
Requires-Dist: pysrt>=1.1.2; extra == 'srt-io-converter'
Provides-Extra: syntactic-relation-extractor
Requires-Dist: spacy>=3.4; extra == 'syntactic-relation-extractor'
Provides-Extra: training
Requires-Dist: torch>=2.1.1; extra == 'training'
Provides-Extra: umls-coder-normalizer
Requires-Dist: feather-format>=0.4; extra == 'umls-coder-normalizer'
Requires-Dist: pandas>=1.4; extra == 'umls-coder-normalizer'
Requires-Dist: torch>=2.1.1; extra == 'umls-coder-normalizer'
Requires-Dist: transformers>=4.21; extra == 'umls-coder-normalizer'
Provides-Extra: webrtc-voice-detector
Requires-Dist: webrtcvad>=2.0; extra == 'webrtc-voice-detector'
